{"nodes": [{"id": "home_mrose_canto_canto_core_jobs_py", "label": "jobs.py", "file_type": "code", "source_file": "canto/core/jobs.py", "source_location": "L1"}, {"id": "core_jobs_joberror", "label": "JobError", "file_type": "code", "source_file": "canto/core/jobs.py", "source_location": "L29"}, {"id": "valueerror", "label": "ValueError", "file_type": "code", "source_file": "", "source_location": ""}, {"id": "core_jobs_id", "label": "_id()", "file_type": "code", "source_file": "canto/core/jobs.py", "source_location": "L33"}, {"id": "core_jobs_jobservice", "label": "JobService", "file_type": "code", "source_file": "canto/core/jobs.py", "source_location": "L38"}, {"id": "core_jobs_jobservice_init", "label": ".__init__()", "file_type": "code", "source_file": "canto/core/jobs.py", "source_location": "L39"}, {"id": "settings", "label": "Settings", "file_type": "code", "source_file": "canto/core/jobs.py", "source_location": "L39"}, {"id": "registry", "label": "Registry", "file_type": "code", "source_file": "canto/core/jobs.py", "source_location": "L39"}, {"id": "statestore", "label": "StateStore", "file_type": "code", "source_file": "canto/core/jobs.py", "source_location": "L39"}, {"id": "credentialvault", "label": "CredentialVault", "file_type": "code", "source_file": "canto/core/jobs.py", "source_location": "L39"}, {"id": "core_jobs_jobservice_event", "label": "._event()", "file_type": "code", "source_file": "canto/core/jobs.py", "source_location": "L58"}, {"id": "any", "label": "Any", "file_type": "code", "source_file": "canto/core/jobs.py", "source_location": "L58"}, {"id": "core_jobs_jobservice_refresh_registry", "label": "._refresh_registry()", "file_type": "code", "source_file": "canto/core/jobs.py", "source_location": "L64"}, {"id": "core_jobs_jobservice_save", "label": "._save()", "file_type": "code", "source_file": "canto/core/jobs.py", "source_location": "L68"}, {"id": "job", "label": "Job", "file_type": "code", "source_file": "canto/core/jobs.py", "source_location": "L68"}, {"id": "core_jobs_jobservice_transition", "label": "._transition()", "file_type": "code", "source_file": "canto/core/jobs.py", "source_location": "L72"}, {"id": "core_jobs_jobservice_validate_inputs", "label": "._validate_inputs()", "file_type": "code", "source_file": "canto/core/jobs.py", "source_location": "L77"}, {"id": "core_jobs_jobservice_checksum", "label": "._checksum()", "file_type": "code", "source_file": "canto/core/jobs.py", "source_location": "L106"}, {"id": "path", "label": "Path", "file_type": "code", "source_file": "canto/core/jobs.py", "source_location": "L106"}, {"id": "core_jobs_jobservice_provider_provenance", "label": "._provider_provenance()", "file_type": "code", "source_file": "canto/core/jobs.py", "source_location": "L109"}, {"id": "core_jobs_jobservice_credential_references", "label": "._credential_references()", "file_type": "code", "source_file": "canto/core/jobs.py", "source_location": "L136"}, {"id": "core_jobs_jobservice_promotion_snapshot", "label": "._promotion_snapshot()", "file_type": "code", "source_file": "canto/core/jobs.py", "source_location": "L142"}, {"id": "core_jobs_jobservice_idempotency_record_key", "label": "._idempotency_record_key()", "file_type": "code", "source_file": "canto/core/jobs.py", "source_location": "L175"}, {"id": "core_jobs_jobservice_validate_promotion", "label": "._validate_promotion()", "file_type": "code", "source_file": "canto/core/jobs.py", "source_location": "L188"}, {"id": "approval", "label": "Approval", "file_type": "code", "source_file": "canto/core/jobs.py", "source_location": "L188"}, {"id": "core_jobs_jobservice_load_artifact_json", "label": "._load_artifact_json()", "file_type": "code", "source_file": "canto/core/jobs.py", "source_location": "L222"}, {"id": "core_jobs_jobservice_pre_write_validate", "label": "._pre_write_validate()", "file_type": "code", "source_file": "canto/core/jobs.py", "source_location": "L231"}, {"id": "core_jobs_jobservice_validate_write_outputs", "label": "._validate_write_outputs()", "file_type": "code", "source_file": "canto/core/jobs.py", "source_location": "L245"}, {"id": "core_jobs_jobservice_validate_recovery", "label": "._validate_recovery()", "file_type": "code", "source_file": "canto/core/jobs.py", "source_location": "L273"}, {"id": "core_jobs_jobservice_promote", "label": ".promote()", "file_type": "code", "source_file": "canto/core/jobs.py", "source_location": "L292"}, {"id": "core_jobs_jobservice_recover", "label": ".recover()", "file_type": "code", "source_file": "canto/core/jobs.py", "source_location": "L327"}, {"id": "core_jobs_jobservice_missing_capability", "label": ".missing_capability()", "file_type": "code", "source_file": "canto/core/jobs.py", "source_location": "L380"}, {"id": "jobrequest", "label": "JobRequest", "file_type": "code", "source_file": "canto/core/jobs.py", "source_location": "L380"}, {"id": "core_jobs_jobservice_create_job", "label": ".create_job()", "file_type": "code", "source_file": "canto/core/jobs.py", "source_location": "L409"}, {"id": "core_jobs_jobservice_process_job", "label": ".process_job()", "file_type": "code", "source_file": "canto/core/jobs.py", "source_location": "L470"}, {"id": "core_jobs_jobservice_fail", "label": "._fail()", "file_type": "code", "source_file": "canto/core/jobs.py", "source_location": "L675"}, {"id": "core_jobs_jobservice_approve", "label": ".approve()", "file_type": "code", "source_file": "canto/core/jobs.py", "source_location": "L682"}, {"id": "core_jobs_jobservice_reject", "label": ".reject()", "file_type": "code", "source_file": "canto/core/jobs.py", "source_location": "L763"}], "edges": [{"source": "home_mrose_canto_canto_core_jobs_py", "target": "hashlib", "relation": "imports", "context": "import", "confidence": "EXTRACTED", "source_file": "canto/core/jobs.py", "source_location": "L3", "weight": 1.0}, {"source": "home_mrose_canto_canto_core_jobs_py", "target": "json", "relation": "imports", "context": "import", "confidence": "EXTRACTED", "source_file": "canto/core/jobs.py", "source_location": "L4", "weight": 1.0}, {"source": "home_mrose_canto_canto_core_jobs_py", "target": "secrets", "relation": "imports", "context": "import", "confidence": "EXTRACTED", "source_file": "canto/core/jobs.py", "source_location": "L5", "weight": 1.0}, {"source": "home_mrose_canto_canto_core_jobs_py", "target": "pathlib", "relation": "imports_from", "context": "import", "confidence": "EXTRACTED", "source_file": "canto/core/jobs.py", "source_location": "L6", "weight": 1.0}, {"source": "home_mrose_canto_canto_core_jobs_py", "target": "typing", "relation": "imports_from", "context": "import", "confidence": "EXTRACTED", "source_file": "canto/core/jobs.py", "source_location": "L7", "weight": 1.0}, {"source": "home_mrose_canto_canto_core_jobs_py", "target": "canto_config", "relation": "imports_from", "context": "import", "confidence": "EXTRACTED", "source_file": "canto/core/jobs.py", "source_location": "L9", "weight": 1.0}, {"source": "home_mrose_canto_canto_core_jobs_py", "target": "canto_core_artifacts", "relation": "imports_from", "context": "import", "confidence": "EXTRACTED", "source_file": "canto/core/jobs.py", "source_location": "L10", "weight": 1.0}, {"source": "home_mrose_canto_canto_core_jobs_py", "target": "canto_core_dependencies", "relation": "imports_from", "context": "import", "confidence": "EXTRACTED", "source_file": "canto/core/jobs.py", "source_location": "L11", "weight": 1.0}, {"source": "home_mrose_canto_canto_core_jobs_py", "target": "canto_core_credentials", "relation": "imports_from", "context": "import", "confidence": "EXTRACTED", "source_file": "canto/core/jobs.py", "source_location": "L12", "weight": 1.0}, {"source": "home_mrose_canto_canto_core_jobs_py", "target": "canto_core_policy", "relation": "imports_from", "context": "import", "confidence": "EXTRACTED", "source_file": "canto/core/jobs.py", "source_location": "L17", "weight": 1.0}, {"source": "home_mrose_canto_canto_core_jobs_py", "target": "canto_core_registry", "relation": "imports_from", "context": "import", "confidence": "EXTRACTED", "source_file": "canto/core/jobs.py", "source_location": "L18", "weight": 1.0}, {"source": "home_mrose_canto_canto_core_jobs_py", "target": "canto_core_runner", "relation": "imports_from", "context": "import", "confidence": "EXTRACTED", "source_file": "canto/core/jobs.py", "source_location": "L19", "weight": 1.0}, {"source": "home_mrose_canto_canto_core_jobs_py", "target": "canto_core_security", "relation": "imports_from", "context": "import", "confidence": "EXTRACTED", "source_file": "canto/core/jobs.py", "source_location": "L20", "weight": 1.0}, {"source": "home_mrose_canto_canto_core_jobs_py", "target": "canto_core_state", "relation": "imports_from", "context": "import", "confidence": "EXTRACTED", "source_file": "canto/core/jobs.py", "source_location": "L25", "weight": 1.0}, {"source": "home_mrose_canto_canto_core_jobs_py", "target": "canto_models_schemas", "relation": "imports_from", "context": "import", "confidence": "EXTRACTED", "source_file": "canto/core/jobs.py", "source_location": "L26", "weight": 1.0}, {"source": "home_mrose_canto_canto_core_jobs_py", "target": "core_jobs_joberror", "relation": "contains", "confidence": "EXTRACTED", "source_file": "canto/core/jobs.py", "source_location": "L29", "weight": 1.0}, {"source": "core_jobs_joberror", "target": "valueerror", "relation": "inherits", "confidence": "EXTRACTED", "source_file": "canto/core/jobs.py", "source_location": "L29", "weight": 1.0}, {"source": "home_mrose_canto_canto_core_jobs_py", "target": "core_jobs_id", "relation": "contains", "confidence": "EXTRACTED", "source_file": "canto/core/jobs.py", "source_location": "L33", "weight": 1.0}, {"source": "home_mrose_canto_canto_core_jobs_py", "target": "core_jobs_jobservice", "relation": "contains", "confidence": "EXTRACTED", "source_file": "canto/core/jobs.py", "source_location": "L38", "weight": 1.0}, {"source": "core_jobs_jobservice", "target": "core_jobs_jobservice_init", "relation": "method", "confidence": "EXTRACTED", "source_file": "canto/core/jobs.py", "source_location": "L39", "weight": 1.0}, {"source": "core_jobs_jobservice_init", "target": "settings", "relation": "references", "context": "parameter_type", "confidence": "EXTRACTED", "source_file": "canto/core/jobs.py", "source_location": "L39", "weight": 1.0}, {"source": "core_jobs_jobservice_init", "target": "registry", "relation": "references", "context": "parameter_type", "confidence": "EXTRACTED", "source_file": "canto/core/jobs.py", "source_location": "L39", "weight": 1.0}, {"source": "core_jobs_jobservice_init", "target": "statestore", "relation": "references", "context": "parameter_type", "confidence": "EXTRACTED", "source_file": "canto/core/jobs.py", "source_location": "L39", "weight": 1.0}, {"source": "core_jobs_jobservice_init", "target": "credentialvault", "relation": "references", "context": "parameter_type", "confidence": "EXTRACTED", "source_file": "canto/core/jobs.py", "source_location": "L39", "weight": 1.0}, {"source": "core_jobs_jobservice", "target": "core_jobs_jobservice_event", "relation": "method", "confidence": "EXTRACTED", "source_file": "canto/core/jobs.py", "source_location": "L58", "weight": 1.0}, {"source": "core_jobs_jobservice_event", "target": "any", "relation": "references", "context": "generic_arg", "confidence": "EXTRACTED", "source_file": "canto/core/jobs.py", "source_location": "L58", "weight": 1.0}, {"source": "core_jobs_jobservice", "target": "core_jobs_jobservice_refresh_registry", "relation": "method", "confidence": "EXTRACTED", "source_file": "canto/core/jobs.py", "source_location": "L64", "weight": 1.0}, {"source": "core_jobs_jobservice", "target": "core_jobs_jobservice_save", "relation": "method", "confidence": "EXTRACTED", "source_file": "canto/core/jobs.py", "source_location": "L68", "weight": 1.0}, {"source": "core_jobs_jobservice_save", "target": "job", "relation": "references", "context": "parameter_type", "confidence": "EXTRACTED", "source_file": "canto/core/jobs.py", "source_location": "L68", "weight": 1.0}, {"source": "core_jobs_jobservice", "target": "core_jobs_jobservice_transition", "relation": "method", "confidence": "EXTRACTED", "source_file": "canto/core/jobs.py", "source_location": "L72", "weight": 1.0}, {"source": "core_jobs_jobservice_transition", "target": "job", "relation": "references", "context": "parameter_type", "confidence": "EXTRACTED", "source_file": "canto/core/jobs.py", "source_location": "L72", "weight": 1.0}, {"source": "core_jobs_jobservice", "target": "core_jobs_jobservice_validate_inputs", "relation": "method", "confidence": "EXTRACTED", "source_file": "canto/core/jobs.py", "source_location": "L77", "weight": 1.0}, {"source": "core_jobs_jobservice_validate_inputs", "target": "any", "relation": "references", "context": "generic_arg", "confidence": "EXTRACTED", "source_file": "canto/core/jobs.py", "source_location": "L77", "weight": 1.0}, {"source": "core_jobs_jobservice_validate_inputs", "target": "any", "relation": "references", "context": "generic_arg", "confidence": "EXTRACTED", "source_file": "canto/core/jobs.py", "source_location": "L77", "weight": 1.0}, {"source": "core_jobs_jobservice_validate_inputs", "target": "any", "relation": "references", "context": "generic_arg", "confidence": "EXTRACTED", "source_file": "canto/core/jobs.py", "source_location": "L77", "weight": 1.0}, {"source": "core_jobs_jobservice", "target": "core_jobs_jobservice_checksum", "relation": "method", "confidence": "EXTRACTED", "source_file": "canto/core/jobs.py", "source_location": "L106", "weight": 1.0}, {"source": "core_jobs_jobservice_checksum", "target": "path", "relation": "references", "context": "parameter_type", "confidence": "EXTRACTED", "source_file": "canto/core/jobs.py", "source_location": "L106", "weight": 1.0}, {"source": "core_jobs_jobservice", "target": "core_jobs_jobservice_provider_provenance", "relation": "method", "confidence": "EXTRACTED", "source_file": "canto/core/jobs.py", "source_location": "L109", "weight": 1.0}, {"source": "core_jobs_jobservice_provider_provenance", "target": "any", "relation": "references", "context": "generic_arg", "confidence": "EXTRACTED", "source_file": "canto/core/jobs.py", "source_location": "L109", "weight": 1.0}, {"source": "core_jobs_jobservice", "target": "core_jobs_jobservice_credential_references", "relation": "method", "confidence": "EXTRACTED", "source_file": "canto/core/jobs.py", "source_location": "L136", "weight": 1.0}, {"source": "core_jobs_jobservice_credential_references", "target": "any", "relation": "references", "context": "generic_arg", "confidence": "EXTRACTED", "source_file": "canto/core/jobs.py", "source_location": "L136", "weight": 1.0}, {"source": "core_jobs_jobservice_credential_references", "target": "any", "relation": "references", "context": "generic_arg", "confidence": "EXTRACTED", "source_file": "canto/core/jobs.py", "source_location": "L136", "weight": 1.0}, {"source": "core_jobs_jobservice", "target": "core_jobs_jobservice_promotion_snapshot", "relation": "method", "confidence": "EXTRACTED", "source_file": "canto/core/jobs.py", "source_location": "L142", "weight": 1.0}, {"source": "core_jobs_jobservice_promotion_snapshot", "target": "job", "relation": "references", "context": "parameter_type", "confidence": "EXTRACTED", "source_file": "canto/core/jobs.py", "source_location": "L142", "weight": 1.0}, {"source": "core_jobs_jobservice_promotion_snapshot", "target": "any", "relation": "references", "context": "generic_arg", "confidence": "EXTRACTED", "source_file": "canto/core/jobs.py", "source_location": "L142", "weight": 1.0}, {"source": "core_jobs_jobservice_promotion_snapshot", "target": "any", "relation": "references", "context": "generic_arg", "confidence": "EXTRACTED", "source_file": "canto/core/jobs.py", "source_location": "L142", "weight": 1.0}, {"source": "core_jobs_jobservice", "target": "core_jobs_jobservice_idempotency_record_key", "relation": "method", "confidence": "EXTRACTED", "source_file": "canto/core/jobs.py", "source_location": "L175", "weight": 1.0}, {"source": "core_jobs_jobservice_idempotency_record_key", "target": "job", "relation": "references", "context": "parameter_type", "confidence": "EXTRACTED", "source_file": "canto/core/jobs.py", "source_location": "L175", "weight": 1.0}, {"source": "core_jobs_jobservice_idempotency_record_key", "target": "any", "relation": "references", "context": "generic_arg", "confidence": "EXTRACTED", "source_file": "canto/core/jobs.py", "source_location": "L175", "weight": 1.0}, {"source": "core_jobs_jobservice", "target": "core_jobs_jobservice_validate_promotion", "relation": "method", "confidence": "EXTRACTED", "source_file": "canto/core/jobs.py", "source_location": "L188", "weight": 1.0}, {"source": "core_jobs_jobservice_validate_promotion", "target": "approval", "relation": "references", "context": "parameter_type", "confidence": "EXTRACTED", "source_file": "canto/core/jobs.py", "source_location": "L188", "weight": 1.0}, {"source": "core_jobs_jobservice_validate_promotion", "target": "any", "relation": "references", "context": "generic_arg", "confidence": "EXTRACTED", "source_file": "canto/core/jobs.py", "source_location": "L188", "weight": 1.0}, {"source": "core_jobs_jobservice_validate_promotion", "target": "any", "relation": "references", "context": "generic_arg", "confidence": "EXTRACTED", "source_file": "canto/core/jobs.py", "source_location": "L188", "weight": 1.0}, {"source": "core_jobs_jobservice", "target": "core_jobs_jobservice_load_artifact_json", "relation": "method", "confidence": "EXTRACTED", "source_file": "canto/core/jobs.py", "source_location": "L222", "weight": 1.0}, {"source": "core_jobs_jobservice_load_artifact_json", "target": "path", "relation": "references", "context": "parameter_type", "confidence": "EXTRACTED", "source_file": "canto/core/jobs.py", "source_location": "L222", "weight": 1.0}, {"source": "core_jobs_jobservice_load_artifact_json", "target": "any", "relation": "references", "context": "generic_arg", "confidence": "EXTRACTED", "source_file": "canto/core/jobs.py", "source_location": "L222", "weight": 1.0}, {"source": "core_jobs_jobservice", "target": "core_jobs_jobservice_pre_write_validate", "relation": "method", "confidence": "EXTRACTED", "source_file": "canto/core/jobs.py", "source_location": "L231", "weight": 1.0}, {"source": "core_jobs_jobservice_pre_write_validate", "target": "job", "relation": "references", "context": "parameter_type", "confidence": "EXTRACTED", "source_file": "canto/core/jobs.py", "source_location": "L231", "weight": 1.0}, {"source": "core_jobs_jobservice", "target": "core_jobs_jobservice_validate_write_outputs", "relation": "method", "confidence": "EXTRACTED", "source_file": "canto/core/jobs.py", "source_location": "L245", "weight": 1.0}, {"source": "core_jobs_jobservice_validate_write_outputs", "target": "job", "relation": "references", "context": "parameter_type", "confidence": "EXTRACTED", "source_file": "canto/core/jobs.py", "source_location": "L245", "weight": 1.0}, {"source": "core_jobs_jobservice_validate_write_outputs", "target": "any", "relation": "references", "context": "generic_arg", "confidence": "EXTRACTED", "source_file": "canto/core/jobs.py", "source_location": "L245", "weight": 1.0}, {"source": "core_jobs_jobservice_validate_write_outputs", "target": "any", "relation": "references", "context": "generic_arg", "confidence": "EXTRACTED", "source_file": "canto/core/jobs.py", "source_location": "L245", "weight": 1.0}, {"source": "core_jobs_jobservice", "target": "core_jobs_jobservice_validate_recovery", "relation": "method", "confidence": "EXTRACTED", "source_file": "canto/core/jobs.py", "source_location": "L273", "weight": 1.0}, {"source": "core_jobs_jobservice_validate_recovery", "target": "approval", "relation": "references", "context": "parameter_type", "confidence": "EXTRACTED", "source_file": "canto/core/jobs.py", "source_location": "L273", "weight": 1.0}, {"source": "core_jobs_jobservice_validate_recovery", "target": "any", "relation": "references", "context": "generic_arg", "confidence": "EXTRACTED", "source_file": "canto/core/jobs.py", "source_location": "L273", "weight": 1.0}, {"source": "core_jobs_jobservice_validate_recovery", "target": "job", "relation": "references", "context": "return_type", "confidence": "EXTRACTED", "source_file": "canto/core/jobs.py", "source_location": "L273", "weight": 1.0}, {"source": "core_jobs_jobservice", "target": "core_jobs_jobservice_promote", "relation": "method", "confidence": "EXTRACTED", "source_file": "canto/core/jobs.py", "source_location": "L292", "weight": 1.0}, {"source": "core_jobs_jobservice_promote", "target": "approval", "relation": "references", "context": "return_type", "confidence": "EXTRACTED", "source_file": "canto/core/jobs.py", "source_location": "L292", "weight": 1.0}, {"source": "core_jobs_jobservice", "target": "core_jobs_jobservice_recover", "relation": "method", "confidence": "EXTRACTED", "source_file": "canto/core/jobs.py", "source_location": "L327", "weight": 1.0}, {"source": "core_jobs_jobservice_recover", "target": "approval", "relation": "references", "context": "return_type", "confidence": "EXTRACTED", "source_file": "canto/core/jobs.py", "source_location": "L327", "weight": 1.0}, {"source": "core_jobs_jobservice", "target": "core_jobs_jobservice_missing_capability", "relation": "method", "confidence": "EXTRACTED", "source_file": "canto/core/jobs.py", "source_location": "L380", "weight": 1.0}, {"source": "core_jobs_jobservice_missing_capability", "target": "jobrequest", "relation": "references", "context": "parameter_type", "confidence": "EXTRACTED", "source_file": "canto/core/jobs.py", "source_location": "L380", "weight": 1.0}, {"source": "core_jobs_jobservice_missing_capability", "target": "any", "relation": "references", "context": "generic_arg", "confidence": "EXTRACTED", "source_file": "canto/core/jobs.py", "source_location": "L380", "weight": 1.0}, {"source": "core_jobs_jobservice", "target": "core_jobs_jobservice_create_job", "relation": "method", "confidence": "EXTRACTED", "source_file": "canto/core/jobs.py", "source_location": "L409", "weight": 1.0}, {"source": "core_jobs_jobservice_create_job", "target": "jobrequest", "relation": "references", "context": "parameter_type", "confidence": "EXTRACTED", "source_file": "canto/core/jobs.py", "source_location": "L409", "weight": 1.0}, {"source": "core_jobs_jobservice_create_job", "target": "any", "relation": "references", "context": "generic_arg", "confidence": "EXTRACTED", "source_file": "canto/core/jobs.py", "source_location": "L409", "weight": 1.0}, {"source": "core_jobs_jobservice_create_job", "target": "job", "relation": "references", "context": "return_type", "confidence": "EXTRACTED", "source_file": "canto/core/jobs.py", "source_location": "L409", "weight": 1.0}, {"source": "core_jobs_jobservice", "target": "core_jobs_jobservice_process_job", "relation": "method", "confidence": "EXTRACTED", "source_file": "canto/core/jobs.py", "source_location": "L470", "weight": 1.0}, {"source": "core_jobs_jobservice_process_job", "target": "job", "relation": "references", "context": "return_type", "confidence": "EXTRACTED", "source_file": "canto/core/jobs.py", "source_location": "L470", "weight": 1.0}, {"source": "core_jobs_jobservice", "target": "core_jobs_jobservice_fail", "relation": "method", "confidence": "EXTRACTED", "source_file": "canto/core/jobs.py", "source_location": "L675", "weight": 1.0}, {"source": "core_jobs_jobservice_fail", "target": "job", "relation": "references", "context": "parameter_type", "confidence": "EXTRACTED", "source_file": "canto/core/jobs.py", "source_location": "L675", "weight": 1.0}, {"source": "core_jobs_jobservice_fail", "target": "any", "relation": "references", "context": "generic_arg", "confidence": "EXTRACTED", "source_file": "canto/core/jobs.py", "source_location": "L675", "weight": 1.0}, {"source": "core_jobs_jobservice_fail", "target": "job", "relation": "references", "context": "return_type", "confidence": "EXTRACTED", "source_file": "canto/core/jobs.py", "source_location": "L675", "weight": 1.0}, {"source": "core_jobs_jobservice", "target": "core_jobs_jobservice_approve", "relation": "method", "confidence": "EXTRACTED", "source_file": "canto/core/jobs.py", "source_location": "L682", "weight": 1.0}, {"source": "core_jobs_jobservice_approve", "target": "job", "relation": "references", "context": "return_type", "confidence": "EXTRACTED", "source_file": "canto/core/jobs.py", "source_location": "L682", "weight": 1.0}, {"source": "core_jobs_jobservice_approve", "target": "approval", "relation": "references", "context": "return_type", "confidence": "EXTRACTED", "source_file": "canto/core/jobs.py", "source_location": "L682", "weight": 1.0}, {"source": "core_jobs_jobservice", "target": "core_jobs_jobservice_reject", "relation": "method", "confidence": "EXTRACTED", "source_file": "canto/core/jobs.py", "source_location": "L763", "weight": 1.0}, {"source": "core_jobs_jobservice_reject", "target": "job", "relation": "references", "context": "return_type", "confidence": "EXTRACTED", "source_file": "canto/core/jobs.py", "source_location": "L763", "weight": 1.0}, {"source": "core_jobs_jobservice_reject", "target": "approval", "relation": "references", "context": "return_type", "confidence": "EXTRACTED", "source_file": "canto/core/jobs.py", "source_location": "L763", "weight": 1.0}, {"source": "core_jobs_jobservice_validate_inputs", "target": "core_jobs_joberror", "relation": "calls", "context": "call", "confidence": "EXTRACTED", "source_file": "canto/core/jobs.py", "source_location": "L81", "weight": 1.0}, {"source": "core_jobs_jobservice_provider_provenance", "target": "path", "relation": "calls", "context": "call", "confidence": "EXTRACTED", "source_file": "canto/core/jobs.py", "source_location": "L110", "weight": 1.0}, {"source": "core_jobs_jobservice_promotion_snapshot", "target": "core_jobs_joberror", "relation": "calls", "context": "call", "confidence": "EXTRACTED", "source_file": "canto/core/jobs.py", "source_location": "L154", "weight": 1.0}, {"source": "core_jobs_jobservice_promotion_snapshot", "target": "path", "relation": "calls", "context": "call", "confidence": "EXTRACTED", "source_file": "canto/core/jobs.py", "source_location": "L155", "weight": 1.0}, {"source": "core_jobs_jobservice_promotion_snapshot", "target": "core_jobs_jobservice_checksum", "relation": "calls", "context": "call", "confidence": "EXTRACTED", "source_file": "canto/core/jobs.py", "source_location": "L159", "weight": 1.0}, {"source": "core_jobs_jobservice_promotion_snapshot", "target": "core_jobs_jobservice_provider_provenance", "relation": "calls", "context": "call", "confidence": "EXTRACTED", "source_file": "canto/core/jobs.py", "source_location": "L165", "weight": 1.0}, {"source": "core_jobs_jobservice_promotion_snapshot", "target": "core_jobs_jobservice_credential_references", "relation": "calls", "context": "call", "confidence": "EXTRACTED", "source_file": "canto/core/jobs.py", "source_location": "L168", "weight": 1.0}, {"source": "core_jobs_jobservice_validate_promotion", "target": "core_jobs_joberror", "relation": "calls", "context": "call", "confidence": "EXTRACTED", "source_file": "canto/core/jobs.py", "source_location": "L196", "weight": 1.0}, {"source": "core_jobs_jobservice_validate_promotion", "target": "core_jobs_jobservice_promotion_snapshot", "relation": "calls", "context": "call", "confidence": "EXTRACTED", "source_file": "canto/core/jobs.py", "source_location": "L203", "weight": 1.0}, {"source": "core_jobs_jobservice_pre_write_validate", "target": "core_jobs_jobservice_load_artifact_json", "relation": "calls", "context": "call", "confidence": "EXTRACTED", "source_file": "canto/core/jobs.py", "source_location": "L233", "weight": 1.0}, {"source": "core_jobs_jobservice_pre_write_validate", "target": "path", "relation": "calls", "context": "call", "confidence": "EXTRACTED", "source_file": "canto/core/jobs.py", "source_location": "L234", "weight": 1.0}, {"source": "core_jobs_jobservice_validate_recovery", "target": "core_jobs_joberror", "relation": "calls", "context": "call", "confidence": "EXTRACTED", "source_file": "canto/core/jobs.py", "source_location": "L278", "weight": 1.0}, {"source": "core_jobs_jobservice_validate_recovery", "target": "core_jobs_jobservice_provider_provenance", "relation": "calls", "context": "call", "confidence": "EXTRACTED", "source_file": "canto/core/jobs.py", "source_location": "L285", "weight": 1.0}, {"source": "core_jobs_jobservice_validate_recovery", "target": "path", "relation": "calls", "context": "call", "confidence": "EXTRACTED", "source_file": "canto/core/jobs.py", "source_location": "L287", "weight": 1.0}, {"source": "core_jobs_jobservice_validate_recovery", "target": "core_jobs_jobservice_checksum", "relation": "calls", "context": "call", "confidence": "EXTRACTED", "source_file": "canto/core/jobs.py", "source_location": "L288", "weight": 1.0}, {"source": "core_jobs_jobservice_promote", "target": "core_jobs_joberror", "relation": "calls", "context": "call", "confidence": "EXTRACTED", "source_file": "canto/core/jobs.py", "source_location": "L295", "weight": 1.0}, {"source": "core_jobs_jobservice_promote", "target": "core_jobs_jobservice_promotion_snapshot", "relation": "calls", "context": "call", "confidence": "EXTRACTED", "source_file": "canto/core/jobs.py", "source_location": "L302", "weight": 1.0}, {"source": "core_jobs_jobservice_promote", "target": "approval", "relation": "calls", "context": "call", "confidence": "EXTRACTED", "source_file": "canto/core/jobs.py", "source_location": "L303", "weight": 1.0}, {"source": "core_jobs_jobservice_promote", "target": "core_jobs_id", "relation": "calls", "context": "call", "confidence": "EXTRACTED", "source_file": "canto/core/jobs.py", "source_location": "L304", "weight": 1.0}, {"source": "core_jobs_jobservice_promote", "target": "core_jobs_jobservice_event", "relation": "calls", "context": "call", "confidence": "EXTRACTED", "source_file": "canto/core/jobs.py", "source_location": "L319", "weight": 1.0}, {"source": "core_jobs_jobservice_recover", "target": "core_jobs_joberror", "relation": "calls", "context": "call", "confidence": "EXTRACTED", "source_file": "canto/core/jobs.py", "source_location": "L330", "weight": 1.0}, {"source": "core_jobs_jobservice_recover", "target": "path", "relation": "calls", "context": "call", "confidence": "EXTRACTED", "source_file": "canto/core/jobs.py", "source_location": "L348", "weight": 1.0}, {"source": "core_jobs_jobservice_recover", "target": "core_jobs_jobservice_provider_provenance", "relation": "calls", "context": "call", "confidence": "EXTRACTED", "source_file": "canto/core/jobs.py", "source_location": "L354", "weight": 1.0}, {"source": "core_jobs_jobservice_recover", "target": "core_jobs_jobservice_checksum", "relation": "calls", "context": "call", "confidence": "EXTRACTED", "source_file": "canto/core/jobs.py", "source_location": "L356", "weight": 1.0}, {"source": "core_jobs_jobservice_recover", "target": "approval", "relation": "calls", "context": "call", "confidence": "EXTRACTED", "source_file": "canto/core/jobs.py", "source_location": "L359", "weight": 1.0}, {"source": "core_jobs_jobservice_recover", "target": "core_jobs_id", "relation": "calls", "context": "call", "confidence": "EXTRACTED", "source_file": "canto/core/jobs.py", "source_location": "L360", "weight": 1.0}, {"source": "core_jobs_jobservice_recover", "target": "core_jobs_jobservice_event", "relation": "calls", "context": "call", "confidence": "EXTRACTED", "source_file": "canto/core/jobs.py", "source_location": "L372", "weight": 1.0}, {"source": "core_jobs_jobservice_missing_capability", "target": "core_jobs_jobservice_refresh_registry", "relation": "calls", "context": "call", "confidence": "EXTRACTED", "source_file": "canto/core/jobs.py", "source_location": "L381", "weight": 1.0}, {"source": "core_jobs_jobservice_create_job", "target": "core_jobs_jobservice_refresh_registry", "relation": "calls", "context": "call", "confidence": "EXTRACTED", "source_file": "canto/core/jobs.py", "source_location": "L412", "weight": 1.0}, {"source": "core_jobs_jobservice_create_job", "target": "core_jobs_joberror", "relation": "calls", "context": "call", "confidence": "EXTRACTED", "source_file": "canto/core/jobs.py", "source_location": "L415", "weight": 1.0}, {"source": "core_jobs_jobservice_create_job", "target": "core_jobs_jobservice_validate_inputs", "relation": "calls", "context": "call", "confidence": "EXTRACTED", "source_file": "canto/core/jobs.py", "source_location": "L416", "weight": 1.0}, {"source": "core_jobs_jobservice_create_job", "target": "core_jobs_jobservice_validate_recovery", "relation": "calls", "context": "call", "confidence": "EXTRACTED", "source_file": "canto/core/jobs.py", "source_location": "L437", "weight": 1.0}, {"source": "core_jobs_jobservice_create_job", "target": "core_jobs_jobservice_validate_promotion", "relation": "calls", "context": "call", "confidence": "EXTRACTED", "source_file": "canto/core/jobs.py", "source_location": "L439", "weight": 1.0}, {"source": "core_jobs_jobservice_create_job", "target": "core_jobs_id", "relation": "calls", "context": "call", "confidence": "EXTRACTED", "source_file": "canto/core/jobs.py", "source_location": "L440", "weight": 1.0}, {"source": "core_jobs_jobservice_create_job", "target": "job", "relation": "calls", "context": "call", "confidence": "EXTRACTED", "source_file": "canto/core/jobs.py", "source_location": "L444", "weight": 1.0}, {"source": "core_jobs_jobservice_create_job", "target": "core_jobs_jobservice_save", "relation": "calls", "context": "call", "confidence": "EXTRACTED", "source_file": "canto/core/jobs.py", "source_location": "L466", "weight": 1.0}, {"source": "core_jobs_jobservice_create_job", "target": "core_jobs_jobservice_event", "relation": "calls", "context": "call", "confidence": "EXTRACTED", "source_file": "canto/core/jobs.py", "source_location": "L467", "weight": 1.0}, {"source": "core_jobs_jobservice_process_job", "target": "core_jobs_jobservice_refresh_registry", "relation": "calls", "context": "call", "confidence": "EXTRACTED", "source_file": "canto/core/jobs.py", "source_location": "L471", "weight": 1.0}, {"source": "core_jobs_jobservice_process_job", "target": "core_jobs_joberror", "relation": "calls", "context": "call", "confidence": "EXTRACTED", "source_file": "canto/core/jobs.py", "source_location": "L474", "weight": 1.0}, {"source": "core_jobs_jobservice_process_job", "target": "core_jobs_jobservice_fail", "relation": "calls", "context": "call", "confidence": "EXTRACTED", "source_file": "canto/core/jobs.py", "source_location": "L480", "weight": 1.0}, {"source": "core_jobs_jobservice_process_job", "target": "core_jobs_jobservice_transition", "relation": "calls", "context": "call", "confidence": "EXTRACTED", "source_file": "canto/core/jobs.py", "source_location": "L486", "weight": 1.0}, {"source": "core_jobs_jobservice_process_job", "target": "core_jobs_jobservice_event", "relation": "calls", "context": "call", "confidence": "EXTRACTED", "source_file": "canto/core/jobs.py", "source_location": "L491", "weight": 1.0}, {"source": "core_jobs_jobservice_process_job", "target": "core_jobs_jobservice_save", "relation": "calls", "context": "call", "confidence": "EXTRACTED", "source_file": "canto/core/jobs.py", "source_location": "L503", "weight": 1.0}, {"source": "core_jobs_jobservice_process_job", "target": "core_jobs_id", "relation": "calls", "context": "call", "confidence": "EXTRACTED", "source_file": "canto/core/jobs.py", "source_location": "L530", "weight": 1.0}, {"source": "core_jobs_jobservice_process_job", "target": "approval", "relation": "calls", "context": "call", "confidence": "EXTRACTED", "source_file": "canto/core/jobs.py", "source_location": "L531", "weight": 1.0}, {"source": "core_jobs_jobservice_process_job", "target": "core_jobs_jobservice_idempotency_record_key", "relation": "calls", "context": "call", "confidence": "EXTRACTED", "source_file": "canto/core/jobs.py", "source_location": "L557", "weight": 1.0}, {"source": "core_jobs_jobservice_process_job", "target": "core_jobs_jobservice_pre_write_validate", "relation": "calls", "context": "call", "confidence": "EXTRACTED", "source_file": "canto/core/jobs.py", "source_location": "L630", "weight": 1.0}, {"source": "core_jobs_jobservice_process_job", "target": "path", "relation": "calls", "context": "call", "confidence": "EXTRACTED", "source_file": "canto/core/jobs.py", "source_location": "L635", "weight": 1.0}, {"source": "core_jobs_jobservice_process_job", "target": "core_jobs_jobservice_validate_write_outputs", "relation": "calls", "context": "call", "confidence": "EXTRACTED", "source_file": "canto/core/jobs.py", "source_location": "L643", "weight": 1.0}, {"source": "core_jobs_jobservice_fail", "target": "core_jobs_jobservice_save", "relation": "calls", "context": "call", "confidence": "EXTRACTED", "source_file": "canto/core/jobs.py", "source_location": "L678", "weight": 1.0}, {"source": "core_jobs_jobservice_fail", "target": "core_jobs_jobservice_event", "relation": "calls", "context": "call", "confidence": "EXTRACTED", "source_file": "canto/core/jobs.py", "source_location": "L679", "weight": 1.0}, {"source": "core_jobs_jobservice_approve", "target": "core_jobs_joberror", "relation": "calls", "context": "call", "confidence": "EXTRACTED", "source_file": "canto/core/jobs.py", "source_location": "L685", "weight": 1.0}, {"source": "core_jobs_jobservice_approve", "target": "core_jobs_jobservice_validate_promotion", "relation": "calls", "context": "call", "confidence": "EXTRACTED", "source_file": "canto/core/jobs.py", "source_location": "L698", "weight": 1.0}, {"source": "core_jobs_jobservice_approve", "target": "core_jobs_jobservice_validate_recovery", "relation": "calls", "context": "call", "confidence": "EXTRACTED", "source_file": "canto/core/jobs.py", "source_location": "L709", "weight": 1.0}, {"source": "core_jobs_jobservice_approve", "target": "core_jobs_jobservice_event", "relation": "calls", "context": "call", "confidence": "EXTRACTED", "source_file": "canto/core/jobs.py", "source_location": "L721", "weight": 1.0}, {"source": "core_jobs_jobservice_approve", "target": "core_jobs_jobservice_process_job", "relation": "calls", "context": "call", "confidence": "EXTRACTED", "source_file": "canto/core/jobs.py", "source_location": "L722", "weight": 1.0}, {"source": "core_jobs_jobservice_approve", "target": "jobrequest", "relation": "calls", "context": "call", "confidence": "EXTRACTED", "source_file": "canto/core/jobs.py", "source_location": "L727", "weight": 1.0}, {"source": "core_jobs_jobservice_approve", "target": "core_jobs_jobservice_create_job", "relation": "calls", "context": "call", "confidence": "EXTRACTED", "source_file": "canto/core/jobs.py", "source_location": "L736", "weight": 1.0}, {"source": "core_jobs_jobservice_reject", "target": "core_jobs_joberror", "relation": "calls", "context": "call", "confidence": "EXTRACTED", "source_file": "canto/core/jobs.py", "source_location": "L766", "weight": 1.0}, {"source": "core_jobs_jobservice_reject", "target": "core_jobs_jobservice_save", "relation": "calls", "context": "call", "confidence": "EXTRACTED", "source_file": "canto/core/jobs.py", "source_location": "L785", "weight": 1.0}, {"source": "core_jobs_jobservice_reject", "target": "core_jobs_jobservice_event", "relation": "calls", "context": "call", "confidence": "EXTRACTED", "source_file": "canto/core/jobs.py", "source_location": "L786", "weight": 1.0}], "raw_calls": [{"caller_nid": "core_jobs_id", "callee": "replace", "is_member_call": true, "source_file": "/home/mrose/canto/canto/core/jobs.py", "source_location": "L34"}, {"caller_nid": "core_jobs_id", "callee": "utc_now", "is_member_call": false, "source_file": "/home/mrose/canto/canto/core/jobs.py", "source_location": "L34"}, {"caller_nid": "core_jobs_id", "callee": "token_hex", "is_member_call": true, "source_file": "/home/mrose/canto/canto/core/jobs.py", "source_location": "L35"}, {"caller_nid": "core_jobs_jobservice_init", "callee": "mkdir", "is_member_call": true, "source_file": "/home/mrose/canto/canto/core/jobs.py", "source_location": "L50"}, {"caller_nid": "core_jobs_jobservice_init", "callee": "mkdir", "is_member_call": true, "source_file": "/home/mrose/canto/canto/core/jobs.py", "source_location": "L51"}, {"caller_nid": "core_jobs_jobservice_init", "callee": "set_registry", "is_member_call": true, "source_file": "/home/mrose/canto/canto/core/jobs.py", "source_location": "L53"}, {"caller_nid": "core_jobs_jobservice_init", "callee": "snapshot", "is_member_call": true, "source_file": "/home/mrose/canto/canto/core/jobs.py", "source_location": "L53"}, {"caller_nid": "core_jobs_jobservice_event", "callee": "append_event", "is_member_call": true, "source_file": "/home/mrose/canto/canto/core/jobs.py", "source_location": "L59"}, {"caller_nid": "core_jobs_jobservice_event", "callee": "utc_now", "is_member_call": false, "source_file": "/home/mrose/canto/canto/core/jobs.py", "source_location": "L61"}, {"caller_nid": "core_jobs_jobservice_refresh_registry", "callee": "refresh_if_changed", "is_member_call": true, "source_file": "/home/mrose/canto/canto/core/jobs.py", "source_location": "L65"}, {"caller_nid": "core_jobs_jobservice_refresh_registry", "callee": "set_registry", "is_member_call": true, "source_file": "/home/mrose/canto/canto/core/jobs.py", "source_location": "L66"}, {"caller_nid": "core_jobs_jobservice_refresh_registry", "callee": "snapshot", "is_member_call": true, "source_file": "/home/mrose/canto/canto/core/jobs.py", "source_location": "L66"}, {"caller_nid": "core_jobs_jobservice_save", "callee": "utc_now", "is_member_call": false, "source_file": "/home/mrose/canto/canto/core/jobs.py", "source_location": "L69"}, {"caller_nid": "core_jobs_jobservice_save", "callee": "set_job", "is_member_call": true, "source_file": "/home/mrose/canto/canto/core/jobs.py", "source_location": "L70"}, {"caller_nid": "core_jobs_jobservice_save", "callee": "model_dump", "is_member_call": true, "source_file": "/home/mrose/canto/canto/core/jobs.py", "source_location": "L70"}, {"caller_nid": "core_jobs_jobservice_transition", "callee": "utc_now", "is_member_call": false, "source_file": "/home/mrose/canto/canto/core/jobs.py", "source_location": "L74"}, {"caller_nid": "core_jobs_jobservice_transition", "callee": "transition_job", "is_member_call": true, "source_file": "/home/mrose/canto/canto/core/jobs.py", "source_location": "L75"}, {"caller_nid": "core_jobs_jobservice_transition", "callee": "model_dump", "is_member_call": true, "source_file": "/home/mrose/canto/canto/core/jobs.py", "source_location": "L75"}, {"caller_nid": "core_jobs_jobservice_validate_inputs", "callee": "get", "is_member_call": true, "source_file": "/home/mrose/canto/canto/core/jobs.py", "source_location": "L78"}, {"caller_nid": "core_jobs_jobservice_validate_inputs", "callee": "items", "is_member_call": true, "source_file": "/home/mrose/canto/canto/core/jobs.py", "source_location": "L83"}, {"caller_nid": "core_jobs_jobservice_validate_inputs", "callee": "get", "is_member_call": true, "source_file": "/home/mrose/canto/canto/core/jobs.py", "source_location": "L88"}, {"caller_nid": "core_jobs_jobservice_validate_inputs", "callee": "get", "is_member_call": true, "source_file": "/home/mrose/canto/canto/core/jobs.py", "source_location": "L92"}, {"caller_nid": "core_jobs_jobservice_validate_inputs", "callee": "get", "is_member_call": true, "source_file": "/home/mrose/canto/canto/core/jobs.py", "source_location": "L93"}, {"caller_nid": "core_jobs_jobservice_checksum", "callee": "hexdigest", "is_member_call": true, "source_file": "/home/mrose/canto/canto/core/jobs.py", "source_location": "L107"}, {"caller_nid": "core_jobs_jobservice_checksum", "callee": "sha256", "is_member_call": true, "source_file": "/home/mrose/canto/canto/core/jobs.py", "source_location": "L107"}, {"caller_nid": "core_jobs_jobservice_checksum", "callee": "read_bytes", "is_member_call": true, "source_file": "/home/mrose/canto/canto/core/jobs.py", "source_location": "L107"}, {"caller_nid": "core_jobs_jobservice_provider_provenance", "callee": "resolve", "is_member_call": true, "source_file": "/home/mrose/canto/canto/core/jobs.py", "source_location": "L110"}, {"caller_nid": "core_jobs_jobservice_provider_provenance", "callee": "load", "is_member_call": true, "source_file": "/home/mrose/canto/canto/core/jobs.py", "source_location": "L113"}, {"caller_nid": "core_jobs_jobservice_provider_provenance", "callee": "resolve", "is_member_call": true, "source_file": "/home/mrose/canto/canto/core/jobs.py", "source_location": "L114"}, {"caller_nid": "core_jobs_jobservice_provider_provenance", "callee": "sha256", "is_member_call": true, "source_file": "/home/mrose/canto/canto/core/jobs.py", "source_location": "L121"}, {"caller_nid": "core_jobs_jobservice_provider_provenance", "callee": "rglob", "is_member_call": true, "source_file": "/home/mrose/canto/canto/core/jobs.py", "source_location": "L122"}, {"caller_nid": "core_jobs_jobservice_provider_provenance", "callee": "is_file", "is_member_call": true, "source_file": "/home/mrose/canto/canto/core/jobs.py", "source_location": "L123"}, {"caller_nid": "core_jobs_jobservice_provider_provenance", "callee": "update", "is_member_call": true, "source_file": "/home/mrose/canto/canto/core/jobs.py", "source_location": "L125"}, {"caller_nid": "core_jobs_jobservice_provider_provenance", "callee": "encode", "is_member_call": true, "source_file": "/home/mrose/canto/canto/core/jobs.py", "source_location": "L125"}, {"caller_nid": "core_jobs_jobservice_provider_provenance", "callee": "as_posix", "is_member_call": true, "source_file": "/home/mrose/canto/canto/core/jobs.py", "source_location": "L125"}, {"caller_nid": "core_jobs_jobservice_provider_provenance", "callee": "relative_to", "is_member_call": true, "source_file": "/home/mrose/canto/canto/core/jobs.py", "source_location": "L125"}, {"caller_nid": "core_jobs_jobservice_provider_provenance", "callee": "update", "is_member_call": true, "source_file": "/home/mrose/canto/canto/core/jobs.py", "source_location": "L126"}, {"caller_nid": "core_jobs_jobservice_provider_provenance", "callee": "update", "is_member_call": true, "source_file": "/home/mrose/canto/canto/core/jobs.py", "source_location": "L127"}, {"caller_nid": "core_jobs_jobservice_provider_provenance", "callee": "read_bytes", "is_member_call": true, "source_file": "/home/mrose/canto/canto/core/jobs.py", "source_location": "L127"}, {"caller_nid": "core_jobs_jobservice_provider_provenance", "callee": "update", "is_member_call": true, "source_file": "/home/mrose/canto/canto/core/jobs.py", "source_location": "L128"}, {"caller_nid": "core_jobs_jobservice_provider_provenance", "callee": "get", "is_member_call": true, "source_file": "/home/mrose/canto/canto/core/jobs.py", "source_location": "L131"}, {"caller_nid": "core_jobs_jobservice_provider_provenance", "callee": "hexdigest", "is_member_call": true, "source_file": "/home/mrose/canto/canto/core/jobs.py", "source_location": "L132"}, {"caller_nid": "core_jobs_jobservice_credential_references", "callee": "get", "is_member_call": true, "source_file": "/home/mrose/canto/canto/core/jobs.py", "source_location": "L139"}, {"caller_nid": "core_jobs_jobservice_credential_references", "callee": "get", "is_member_call": true, "source_file": "/home/mrose/canto/canto/core/jobs.py", "source_location": "L139"}, {"caller_nid": "core_jobs_jobservice_promotion_snapshot", "callee": "get_artifacts", "is_member_call": true, "source_file": "/home/mrose/canto/canto/core/jobs.py", "source_location": "L147"}, {"caller_nid": "core_jobs_jobservice_promotion_snapshot", "callee": "get", "is_member_call": true, "source_file": "/home/mrose/canto/canto/core/jobs.py", "source_location": "L152"}, {"caller_nid": "core_jobs_jobservice_promotion_snapshot", "callee": "is_file", "is_member_call": true, "source_file": "/home/mrose/canto/canto/core/jobs.py", "source_location": "L156"}, {"caller_nid": "core_jobs_jobservice_promotion_snapshot", "callee": "resolve", "is_member_call": true, "source_file": "/home/mrose/canto/canto/core/jobs.py", "source_location": "L158"}, {"caller_nid": "core_jobs_jobservice_promotion_snapshot", "callee": "hexdigest", "is_member_call": true, "source_file": "/home/mrose/canto/canto/core/jobs.py", "source_location": "L169"}, {"caller_nid": "core_jobs_jobservice_promotion_snapshot", "callee": "sha256", "is_member_call": true, "source_file": "/home/mrose/canto/canto/core/jobs.py", "source_location": "L169"}, {"caller_nid": "core_jobs_jobservice_promotion_snapshot", "callee": "encode", "is_member_call": true, "source_file": "/home/mrose/canto/canto/core/jobs.py", "source_location": "L170"}, {"caller_nid": "core_jobs_jobservice_promotion_snapshot", "callee": "dumps", "is_member_call": true, "source_file": "/home/mrose/canto/canto/core/jobs.py", "source_location": "L170"}, {"caller_nid": "core_jobs_jobservice_idempotency_record_key", "callee": "join", "is_member_call": true, "source_file": "/home/mrose/canto/canto/core/jobs.py", "source_location": "L179"}, {"caller_nid": "core_jobs_jobservice_validate_promotion", "callee": "get_job", "is_member_call": true, "source_file": "/home/mrose/canto/canto/core/jobs.py", "source_location": "L197"}, {"caller_nid": "core_jobs_jobservice_validate_promotion", "callee": "model_validate", "is_member_call": true, "source_file": "/home/mrose/canto/canto/core/jobs.py", "source_location": "L200"}, {"caller_nid": "core_jobs_jobservice_load_artifact_json", "callee": "loads", "is_member_call": true, "source_file": "/home/mrose/canto/canto/core/jobs.py", "source_location": "L224"}, {"caller_nid": "core_jobs_jobservice_load_artifact_json", "callee": "read_text", "is_member_call": true, "source_file": "/home/mrose/canto/canto/core/jobs.py", "source_location": "L224"}, {"caller_nid": "core_jobs_jobservice_load_artifact_json", "callee": "ArtifactError", "is_member_call": false, "source_file": "/home/mrose/canto/canto/core/jobs.py", "source_location": "L226"}, {"caller_nid": "core_jobs_jobservice_load_artifact_json", "callee": "ArtifactError", "is_member_call": false, "source_file": "/home/mrose/canto/canto/core/jobs.py", "source_location": "L228"}, {"caller_nid": "core_jobs_jobservice_pre_write_validate", "callee": "get", "is_member_call": true, "source_file": "/home/mrose/canto/canto/core/jobs.py", "source_location": "L236"}, {"caller_nid": "core_jobs_jobservice_pre_write_validate", "callee": "ArtifactError", "is_member_call": false, "source_file": "/home/mrose/canto/canto/core/jobs.py", "source_location": "L237"}, {"caller_nid": "core_jobs_jobservice_pre_write_validate", "callee": "get", "is_member_call": true, "source_file": "/home/mrose/canto/canto/core/jobs.py", "source_location": "L242"}, {"caller_nid": "core_jobs_jobservice_pre_write_validate", "callee": "ArtifactError", "is_member_call": false, "source_file": "/home/mrose/canto/canto/core/jobs.py", "source_location": "L243"}, {"caller_nid": "core_jobs_jobservice_validate_write_outputs", "callee": "load", "is_member_call": false, "source_file": "/home/mrose/canto/canto/core/jobs.py", "source_location": "L258"}, {"caller_nid": "core_jobs_jobservice_validate_write_outputs", "callee": "get", "is_member_call": true, "source_file": "/home/mrose/canto/canto/core/jobs.py", "source_location": "L259"}, {"caller_nid": "core_jobs_jobservice_validate_write_outputs", "callee": "ArtifactError", "is_member_call": false, "source_file": "/home/mrose/canto/canto/core/jobs.py", "source_location": "L260"}, {"caller_nid": "core_jobs_jobservice_validate_write_outputs", "callee": "load", "is_member_call": false, "source_file": "/home/mrose/canto/canto/core/jobs.py", "source_location": "L263"}, {"caller_nid": "core_jobs_jobservice_validate_write_outputs", "callee": "get", "is_member_call": true, "source_file": "/home/mrose/canto/canto/core/jobs.py", "source_location": "L264"}, {"caller_nid": "core_jobs_jobservice_validate_write_outputs", "callee": "ArtifactError", "is_member_call": false, "source_file": "/home/mrose/canto/canto/core/jobs.py", "source_location": "L265"}, {"caller_nid": "core_jobs_jobservice_validate_write_outputs", "callee": "load", "is_member_call": false, "source_file": "/home/mrose/canto/canto/core/jobs.py", "source_location": "L266"}, {"caller_nid": "core_jobs_jobservice_validate_write_outputs", "callee": "get", "is_member_call": true, "source_file": "/home/mrose/canto/canto/core/jobs.py", "source_location": "L268"}, {"caller_nid": "core_jobs_jobservice_validate_write_outputs", "callee": "ArtifactError", "is_member_call": false, "source_file": "/home/mrose/canto/canto/core/jobs.py", "source_location": "L269"}, {"caller_nid": "core_jobs_jobservice_validate_recovery", "callee": "get_job", "is_member_call": true, "source_file": "/home/mrose/canto/canto/core/jobs.py", "source_location": "L279"}, {"caller_nid": "core_jobs_jobservice_validate_recovery", "callee": "model_validate", "is_member_call": true, "source_file": "/home/mrose/canto/canto/core/jobs.py", "source_location": "L282"}, {"caller_nid": "core_jobs_jobservice_validate_recovery", "callee": "is_file", "is_member_call": true, "source_file": "/home/mrose/canto/canto/core/jobs.py", "source_location": "L288"}, {"caller_nid": "core_jobs_jobservice_promote", "callee": "get_job", "is_member_call": true, "source_file": "/home/mrose/canto/canto/core/jobs.py", "source_location": "L293"}, {"caller_nid": "core_jobs_jobservice_promote", "callee": "model_validate", "is_member_call": true, "source_file": "/home/mrose/canto/canto/core/jobs.py", "source_location": "L296"}, {"caller_nid": "core_jobs_jobservice_promote", "callee": "provider_internal", "is_member_call": true, "source_file": "/home/mrose/canto/canto/core/jobs.py", "source_location": "L299"}, {"caller_nid": "core_jobs_jobservice_promote", "callee": "get", "is_member_call": true, "source_file": "/home/mrose/canto/canto/core/jobs.py", "source_location": "L311"}, {"caller_nid": "core_jobs_jobservice_promote", "callee": "utc_now", "is_member_call": false, "source_file": "/home/mrose/canto/canto/core/jobs.py", "source_location": "L312"}, {"caller_nid": "core_jobs_jobservice_promote", "callee": "utc_now", "is_member_call": false, "source_file": "/home/mrose/canto/canto/core/jobs.py", "source_location": "L313"}, {"caller_nid": "core_jobs_jobservice_promote", "callee": "set_approval", "is_member_call": true, "source_file": "/home/mrose/canto/canto/core/jobs.py", "source_location": "L316"}, {"caller_nid": "core_jobs_jobservice_promote", "callee": "model_dump", "is_member_call": true, "source_file": "/home/mrose/canto/canto/core/jobs.py", "source_location": "L317"}, {"caller_nid": "core_jobs_jobservice_recover", "callee": "get_job", "is_member_call": true, "source_file": "/home/mrose/canto/canto/core/jobs.py", "source_location": "L328"}, {"caller_nid": "core_jobs_jobservice_recover", "callee": "model_validate", "is_member_call": true, "source_file": "/home/mrose/canto/canto/core/jobs.py", "source_location": "L331"}, {"caller_nid": "core_jobs_jobservice_recover", "callee": "provider_internal", "is_member_call": true, "source_file": "/home/mrose/canto/canto/core/jobs.py", "source_location": "L334"}, {"caller_nid": "core_jobs_jobservice_recover", "callee": "get", "is_member_call": true, "source_file": "/home/mrose/canto/canto/core/jobs.py", "source_location": "L335"}, {"caller_nid": "core_jobs_jobservice_recover", "callee": "get", "is_member_call": true, "source_file": "/home/mrose/canto/canto/core/jobs.py", "source_location": "L335"}, {"caller_nid": "core_jobs_jobservice_recover", "callee": "get", "is_member_call": true, "source_file": "/home/mrose/canto/canto/core/jobs.py", "source_location": "L335"}, {"caller_nid": "core_jobs_jobservice_recover", "callee": "get_artifacts", "is_member_call": true, "source_file": "/home/mrose/canto/canto/core/jobs.py", "source_location": "L343"}, {"caller_nid": "core_jobs_jobservice_recover", "callee": "is_file", "is_member_call": true, "source_file": "/home/mrose/canto/canto/core/jobs.py", "source_location": "L348"}, {"caller_nid": "core_jobs_jobservice_recover", "callee": "resolve", "is_member_call": true, "source_file": "/home/mrose/canto/canto/core/jobs.py", "source_location": "L355"}, {"caller_nid": "core_jobs_jobservice_recover", "callee": "get", "is_member_call": true, "source_file": "/home/mrose/canto/canto/core/jobs.py", "source_location": "L364"}, {"caller_nid": "core_jobs_jobservice_recover", "callee": "utc_now", "is_member_call": false, "source_file": "/home/mrose/canto/canto/core/jobs.py", "source_location": "L365"}, {"caller_nid": "core_jobs_jobservice_recover", "callee": "utc_now", "is_member_call": false, "source_file": "/home/mrose/canto/canto/core/jobs.py", "source_location": "L366"}, {"caller_nid": "core_jobs_jobservice_recover", "callee": "set_approval", "is_member_call": true, "source_file": "/home/mrose/canto/canto/core/jobs.py", "source_location": "L369"}, {"caller_nid": "core_jobs_jobservice_recover", "callee": "model_dump", "is_member_call": true, "source_file": "/home/mrose/canto/canto/core/jobs.py", "source_location": "L370"}, {"caller_nid": "core_jobs_jobservice_create_job", "callee": "provider_internal", "is_member_call": true, "source_file": "/home/mrose/canto/canto/core/jobs.py", "source_location": "L413"}, {"caller_nid": "core_jobs_jobservice_create_job", "callee": "validate_sensitive_inputs", "is_member_call": false, "source_file": "/home/mrose/canto/canto/core/jobs.py", "source_location": "L418"}, {"caller_nid": "core_jobs_jobservice_create_job", "callee": "get_approval", "is_member_call": true, "source_file": "/home/mrose/canto/canto/core/jobs.py", "source_location": "L423"}, {"caller_nid": "core_jobs_jobservice_create_job", "callee": "model_validate", "is_member_call": true, "source_file": "/home/mrose/canto/canto/core/jobs.py", "source_location": "L426"}, {"caller_nid": "core_jobs_jobservice_create_job", "callee": "resolve", "is_member_call": true, "source_file": "/home/mrose/canto/canto/core/jobs.py", "source_location": "L441"}, {"caller_nid": "core_jobs_jobservice_create_job", "callee": "mkdir", "is_member_call": true, "source_file": "/home/mrose/canto/canto/core/jobs.py", "source_location": "L442"}, {"caller_nid": "core_jobs_jobservice_create_job", "callee": "utc_now", "is_member_call": false, "source_file": "/home/mrose/canto/canto/core/jobs.py", "source_location": "L443"}, {"caller_nid": "core_jobs_jobservice_create_job", "callee": "set_approval", "is_member_call": true, "source_file": "/home/mrose/canto/canto/core/jobs.py", "source_location": "L463"}, {"caller_nid": "core_jobs_jobservice_create_job", "callee": "model_dump", "is_member_call": true, "source_file": "/home/mrose/canto/canto/core/jobs.py", "source_location": "L464"}, {"caller_nid": "core_jobs_jobservice_process_job", "callee": "get_job", "is_member_call": true, "source_file": "/home/mrose/canto/canto/core/jobs.py", "source_location": "L472"}, {"caller_nid": "core_jobs_jobservice_process_job", "callee": "model_validate", "is_member_call": true, "source_file": "/home/mrose/canto/canto/core/jobs.py", "source_location": "L475"}, {"caller_nid": "core_jobs_jobservice_process_job", "callee": "provider_internal", "is_member_call": true, "source_file": "/home/mrose/canto/canto/core/jobs.py", "source_location": "L478"}, {"caller_nid": "core_jobs_jobservice_process_job", "callee": "get_approval", "is_member_call": true, "source_file": "/home/mrose/canto/canto/core/jobs.py", "source_location": "L483"}, {"caller_nid": "core_jobs_jobservice_process_job", "callee": "get", "is_member_call": true, "source_file": "/home/mrose/canto/canto/core/jobs.py", "source_location": "L484"}, {"caller_nid": "core_jobs_jobservice_process_job", "callee": "model_validate", "is_member_call": true, "source_file": "/home/mrose/canto/canto/core/jobs.py", "source_location": "L487"}, {"caller_nid": "core_jobs_jobservice_process_job", "callee": "get_job", "is_member_call": true, "source_file": "/home/mrose/canto/canto/core/jobs.py", "source_location": "L487"}, {"caller_nid": "core_jobs_jobservice_process_job", "callee": "model_validate", "is_member_call": true, "source_file": "/home/mrose/canto/canto/core/jobs.py", "source_location": "L490"}, {"caller_nid": "core_jobs_jobservice_process_job", "callee": "get_job", "is_member_call": true, "source_file": "/home/mrose/canto/canto/core/jobs.py", "source_location": "L490"}, {"caller_nid": "core_jobs_jobservice_process_job", "callee": "get", "is_member_call": true, "source_file": "/home/mrose/canto/canto/core/jobs.py", "source_location": "L493"}, {"caller_nid": "core_jobs_jobservice_process_job", "callee": "get", "is_member_call": true, "source_file": "/home/mrose/canto/canto/core/jobs.py", "source_location": "L494"}, {"caller_nid": "core_jobs_jobservice_process_job", "callee": "append", "is_member_call": true, "source_file": "/home/mrose/canto/canto/core/jobs.py", "source_location": "L497"}, {"caller_nid": "core_jobs_jobservice_process_job", "callee": "check_dependencies", "is_member_call": false, "source_file": "/home/mrose/canto/canto/core/jobs.py", "source_location": "L498"}, {"caller_nid": "core_jobs_jobservice_process_job", "callee": "evaluate_policy", "is_member_call": false, "source_file": "/home/mrose/canto/canto/core/jobs.py", "source_location": "L506"}, {"caller_nid": "core_jobs_jobservice_process_job", "callee": "get_approval", "is_member_call": true, "source_file": "/home/mrose/canto/canto/core/jobs.py", "source_location": "L511"}, {"caller_nid": "core_jobs_jobservice_process_job", "callee": "get", "is_member_call": true, "source_file": "/home/mrose/canto/canto/core/jobs.py", "source_location": "L512"}, {"caller_nid": "core_jobs_jobservice_process_job", "callee": "model_validate", "is_member_call": true, "source_file": "/home/mrose/canto/canto/core/jobs.py", "source_location": "L517"}, {"caller_nid": "core_jobs_jobservice_process_job", "callee": "get_job", "is_member_call": true, "source_file": "/home/mrose/canto/canto/core/jobs.py", "source_location": "L517"}, {"caller_nid": "core_jobs_jobservice_process_job", "callee": "join", "is_member_call": true, "source_file": "/home/mrose/canto/canto/core/jobs.py", "source_location": "L536"}, {"caller_nid": "core_jobs_jobservice_process_job", "callee": "get", "is_member_call": true, "source_file": "/home/mrose/canto/canto/core/jobs.py", "source_location": "L537"}, {"caller_nid": "core_jobs_jobservice_process_job", "callee": "utc_now", "is_member_call": false, "source_file": "/home/mrose/canto/canto/core/jobs.py", "source_location": "L538"}, {"caller_nid": "core_jobs_jobservice_process_job", "callee": "utc_now", "is_member_call": false, "source_file": "/home/mrose/canto/canto/core/jobs.py", "source_location": "L539"}, {"caller_nid": "core_jobs_jobservice_process_job", "callee": "set_approval", "is_member_call": true, "source_file": "/home/mrose/canto/canto/core/jobs.py", "source_location": "L541"}, {"caller_nid": "core_jobs_jobservice_process_job", "callee": "model_dump", "is_member_call": true, "source_file": "/home/mrose/canto/canto/core/jobs.py", "source_location": "L541"}, {"caller_nid": "core_jobs_jobservice_process_job", "callee": "model_validate", "is_member_call": true, "source_file": "/home/mrose/canto/canto/core/jobs.py", "source_location": "L552"}, {"caller_nid": "core_jobs_jobservice_process_job", "callee": "get_job", "is_member_call": true, "source_file": "/home/mrose/canto/canto/core/jobs.py", "source_location": "L552"}, {"caller_nid": "core_jobs_jobservice_process_job", "callee": "claim_idempotency", "is_member_call": true, "source_file": "/home/mrose/canto/canto/core/jobs.py", "source_location": "L563"}, {"caller_nid": "core_jobs_jobservice_process_job", "callee": "get", "is_member_call": true, "source_file": "/home/mrose/canto/canto/core/jobs.py", "source_location": "L566"}, {"caller_nid": "core_jobs_jobservice_process_job", "callee": "get", "is_member_call": true, "source_file": "/home/mrose/canto/canto/core/jobs.py", "source_location": "L574"}, {"caller_nid": "core_jobs_jobservice_process_job", "callee": "set_artifacts", "is_member_call": true, "source_file": "/home/mrose/canto/canto/core/jobs.py", "source_location": "L576"}, {"caller_nid": "core_jobs_jobservice_process_job", "callee": "get_artifacts", "is_member_call": true, "source_file": "/home/mrose/canto/canto/core/jobs.py", "source_location": "L577"}, {"caller_nid": "core_jobs_jobservice_process_job", "callee": "effective_limits", "is_member_call": false, "source_file": "/home/mrose/canto/canto/core/jobs.py", "source_location": "L601"}, {"caller_nid": "core_jobs_jobservice_process_job", "callee": "resolve_credential_inputs", "is_member_call": false, "source_file": "/home/mrose/canto/canto/core/jobs.py", "source_location": "L611"}, {"caller_nid": "core_jobs_jobservice_process_job", "callee": "local", "is_member_call": true, "source_file": "/home/mrose/canto/canto/core/jobs.py", "source_location": "L612"}, {"caller_nid": "core_jobs_jobservice_process_job", "callee": "model_dump", "is_member_call": true, "source_file": "/home/mrose/canto/canto/core/jobs.py", "source_location": "L621"}, {"caller_nid": "core_jobs_jobservice_process_job", "callee": "resolve", "is_member_call": true, "source_file": "/home/mrose/canto/canto/core/jobs.py", "source_location": "L625"}, {"caller_nid": "core_jobs_jobservice_process_job", "callee": "resolve", "is_member_call": true, "source_file": "/home/mrose/canto/canto/core/jobs.py", "source_location": "L626"}, {"caller_nid": "core_jobs_jobservice_process_job", "callee": "run_provider", "is_member_call": false, "source_file": "/home/mrose/canto/canto/core/jobs.py", "source_location": "L632"}, {"caller_nid": "core_jobs_jobservice_process_job", "callee": "redact_artifacts", "is_member_call": false, "source_file": "/home/mrose/canto/canto/core/jobs.py", "source_location": "L640"}, {"caller_nid": "core_jobs_jobservice_process_job", "callee": "collect_artifacts", "is_member_call": false, "source_file": "/home/mrose/canto/canto/core/jobs.py", "source_location": "L641"}, {"caller_nid": "core_jobs_jobservice_process_job", "callee": "get", "is_member_call": true, "source_file": "/home/mrose/canto/canto/core/jobs.py", "source_location": "L641"}, {"caller_nid": "core_jobs_jobservice_process_job", "callee": "set_idempotency", "is_member_call": true, "source_file": "/home/mrose/canto/canto/core/jobs.py", "source_location": "L647"}, {"caller_nid": "core_jobs_jobservice_process_job", "callee": "set_artifacts", "is_member_call": true, "source_file": "/home/mrose/canto/canto/core/jobs.py", "source_location": "L658"}, {"caller_nid": "core_jobs_jobservice_process_job", "callee": "set_idempotency", "is_member_call": true, "source_file": "/home/mrose/canto/canto/core/jobs.py", "source_location": "L663"}, {"caller_nid": "core_jobs_jobservice_process_job", "callee": "get", "is_member_call": true, "source_file": "/home/mrose/canto/canto/core/jobs.py", "source_location": "L672"}, {"caller_nid": "core_jobs_jobservice_approve", "callee": "get_approval", "is_member_call": true, "source_file": "/home/mrose/canto/canto/core/jobs.py", "source_location": "L683"}, {"caller_nid": "core_jobs_jobservice_approve", "callee": "model_validate", "is_member_call": true, "source_file": "/home/mrose/canto/canto/core/jobs.py", "source_location": "L686"}, {"caller_nid": "core_jobs_jobservice_approve", "callee": "model_validate", "is_member_call": true, "source_file": "/home/mrose/canto/canto/core/jobs.py", "source_location": "L690"}, {"caller_nid": "core_jobs_jobservice_approve", "callee": "get_job", "is_member_call": true, "source_file": "/home/mrose/canto/canto/core/jobs.py", "source_location": "L691"}, {"caller_nid": "core_jobs_jobservice_approve", "callee": "provider_internal", "is_member_call": true, "source_file": "/home/mrose/canto/canto/core/jobs.py", "source_location": "L693"}, {"caller_nid": "core_jobs_jobservice_approve", "callee": "get_job", "is_member_call": true, "source_file": "/home/mrose/canto/canto/core/jobs.py", "source_location": "L700"}, {"caller_nid": "core_jobs_jobservice_approve", "callee": "model_validate", "is_member_call": true, "source_file": "/home/mrose/canto/canto/core/jobs.py", "source_location": "L703"}, {"caller_nid": "core_jobs_jobservice_approve", "callee": "provider_internal", "is_member_call": true, "source_file": "/home/mrose/canto/canto/core/jobs.py", "source_location": "L704"}, {"caller_nid": "core_jobs_jobservice_approve", "callee": "utc_now", "is_member_call": false, "source_file": "/home/mrose/canto/canto/core/jobs.py", "source_location": "L711"}, {"caller_nid": "core_jobs_jobservice_approve", "callee": "transition_approval", "is_member_call": true, "source_file": "/home/mrose/canto/canto/core/jobs.py", "source_location": "L714"}, {"caller_nid": "core_jobs_jobservice_approve", "callee": "model_dump", "is_member_call": true, "source_file": "/home/mrose/canto/canto/core/jobs.py", "source_location": "L715"}, {"caller_nid": "core_jobs_jobservice_approve", "callee": "get_approval", "is_member_call": true, "source_file": "/home/mrose/canto/canto/core/jobs.py", "source_location": "L717"}, {"caller_nid": "core_jobs_jobservice_approve", "callee": "get", "is_member_call": true, "source_file": "/home/mrose/canto/canto/core/jobs.py", "source_location": "L718"}, {"caller_nid": "core_jobs_jobservice_approve", "callee": "model_validate", "is_member_call": true, "source_file": "/home/mrose/canto/canto/core/jobs.py", "source_location": "L724"}, {"caller_nid": "core_jobs_jobservice_approve", "callee": "get_job", "is_member_call": true, "source_file": "/home/mrose/canto/canto/core/jobs.py", "source_location": "L725"}, {"caller_nid": "core_jobs_jobservice_approve", "callee": "model_copy", "is_member_call": true, "source_file": "/home/mrose/canto/canto/core/jobs.py", "source_location": "L732"}, {"caller_nid": "core_jobs_jobservice_approve", "callee": "model_validate", "is_member_call": true, "source_file": "/home/mrose/canto/canto/core/jobs.py", "source_location": "L745"}, {"caller_nid": "core_jobs_jobservice_approve", "callee": "get_job", "is_member_call": true, "source_file": "/home/mrose/canto/canto/core/jobs.py", "source_location": "L746"}, {"caller_nid": "core_jobs_jobservice_reject", "callee": "get_approval", "is_member_call": true, "source_file": "/home/mrose/canto/canto/core/jobs.py", "source_location": "L764"}, {"caller_nid": "core_jobs_jobservice_reject", "callee": "model_validate", "is_member_call": true, "source_file": "/home/mrose/canto/canto/core/jobs.py", "source_location": "L767"}, {"caller_nid": "core_jobs_jobservice_reject", "callee": "utc_now", "is_member_call": false, "source_file": "/home/mrose/canto/canto/core/jobs.py", "source_location": "L771"}, {"caller_nid": "core_jobs_jobservice_reject", "callee": "transition_approval", "is_member_call": true, "source_file": "/home/mrose/canto/canto/core/jobs.py", "source_location": "L774"}, {"caller_nid": "core_jobs_jobservice_reject", "callee": "model_dump", "is_member_call": true, "source_file": "/home/mrose/canto/canto/core/jobs.py", "source_location": "L775"}, {"caller_nid": "core_jobs_jobservice_reject", "callee": "get_approval", "is_member_call": true, "source_file": "/home/mrose/canto/canto/core/jobs.py", "source_location": "L777"}, {"caller_nid": "core_jobs_jobservice_reject", "callee": "get", "is_member_call": true, "source_file": "/home/mrose/canto/canto/core/jobs.py", "source_location": "L778"}, {"caller_nid": "core_jobs_jobservice_reject", "callee": "model_validate", "is_member_call": true, "source_file": "/home/mrose/canto/canto/core/jobs.py", "source_location": "L782"}, {"caller_nid": "core_jobs_jobservice_reject", "callee": "get_job", "is_member_call": true, "source_file": "/home/mrose/canto/canto/core/jobs.py", "source_location": "L782"}]}